{
  "page": 1,
  "results": [
    {
      "adult": false,
      "backdrop_path": "/ftGzl2GCyko61Qp161bQElN2Uzd.jpg",
      "genre_ids": [28, 53],
      "id": 961484,
      "original_language": "en",
      "original_title": "Last Seen Alive",
      "overview": "After Will Spann's wife suddenly vanishes at a gas station, his desperate search to find her leads him down a dark path that forces him to run from authorities and take the law into his own hands.",
      "popularity": 133.804,
      "poster_path": "/qvqyDj34Uivokf4qIvK4bH0m0qF.jpg",
      "release_date": "2022-05-19",
      "title": "Last Seen Alive",
      "video": false,
      "vote_average": 6.6,
      "vote_count": 657
    },
    {
      "adult": false,
      "backdrop_path": "/lV3UFPPxDIPelh46G9oySXN9Mcz.jpg",
      "genre_ids": [10749, 18],
      "id": 744275,
      "original_language": "en",
      "original_title": "After We Fell",
      "overview": "Just as Tessa's life begins to become unglued, nothing is what she thought it would be. Not her friends nor her family. The only person that she should be able to rely on is Hardin, who is furious when he discovers the massive secret that she's been keeping. Before Tessa makes the biggest decision of her life, everything changes because of revelations about her family.",
      "popularity": 114.105,
      "poster_path": "/dU4HfnTEJDf9KvxGS9hgO7BVeju.jpg",
      "release_date": "2021-09-01",
      "title": "After We Fell",
      "video": false,
      "vote_average": 7.1,
      "vote_count": 2128
    },
    {
      "adult": false,
      "backdrop_path": "/t4To8feUSysyBs4tlBAbXIrKlCv.jpg",
      "genre_ids": [28, 53],
      "id": 860623,
      "original_language": "en",
      "original_title": "Last Man Down",
      "overview": "After civilization succumbs to a deadly pandemic and his wife is murdered, a special forces soldier abandons his duty and becomes a hermit in the Nordic wilderness. Years later, a wounded woman appears on his doorstep. She's escaped from a lab and her pursuers believe her blood is the key to a worldwide cure. He's hesitant to get involved, but all doubts are cast aside when he discovers her pursuer is none other than Commander Stone, the man that murdered his wife some years ago.",
      "popularity": 111.533,
      "poster_path": "/4B7liCxNCZIZGONmAMkCnxVlZQV.jpg",
      "release_date": "2022-11-03",
      "title": "Last Man Down",
      "video": false,
      "vote_average": 5.9,
      "vote_count": 34
    },
    {
      "adult": false,
      "backdrop_path": "/il9nvQH3f92n5bBKJfpjfaHXFYi.jpg",
      "genre_ids": [28, 80, 18, 12, 53],
      "id": 539885,
      "original_language": "en",
      "original_title": "Ava",
      "overview": "A black ops assassin is forced to fight for her own survival after a job goes dangerously wrong.",
      "popularity": 59.202,
      "poster_path": "/qzA87Wf4jo1h8JMk9GilyIYvwsA.jpg",
      "release_date": "2020-07-02",
      "title": "Ava",
      "video": false,
      "vote_average": 5.8,
      "vote_count": 2185
    },
    {
      "adult": false,
      "backdrop_path": "/zHHcindG4uVZLPLuYWoo4rnv6Ti.jpg",
      "genre_ids": [18, 28, 53],
      "id": 595743,
      "original_language": "en",
      "original_title": "SAS: Red Notice",
      "overview": "An off-duty SAS soldier, Tom Buckingham, must thwart a terror attack on a train running through the Channel Tunnel. As the action escalates on the train, events transpire in the corridors of power that may make the difference as to whether Buckingham and the civilian passengers make it out of the tunnel alive.",
      "popularity": 39.801,
      "poster_path": "/6Y9fl8tD1xtyUrOHV2MkCYTpzgi.jpg",
      "release_date": "2021-08-11",
      "title": "SAS: Red Notice",
      "video": false,
      "vote_average": 5.8,
      "vote_count": 428
    },
    {
      "adult": false,
      "backdrop_path": "/19Shb0Xn0PeLXA4CkT2TIIvxaR6.jpg",
      "genre_ids": [28, 18, 36],
      "id": 365222,
      "original_language": "cn",
      "original_title": "葉問3",
      "overview": "When a band of brutal gangsters led by a crooked property developer make a play to take over the city, Master Ip is forced to take a stand.",
      "popularity": 30.406,
      "poster_path": "/RTt4lgyTDI8JHMGbZGDDbcZmkM.jpg",
      "release_date": "2015-12-24",
      "title": "Ip Man 3",
      "video": false,
      "vote_average": 7,
      "vote_count": 1449
    },
    {
      "adult": false,
      "backdrop_path": "/4EtSV3LmwHQSlmAeyn9pJ3ANtC8.jpg",
      "genre_ids": [28],
      "id": 513691,
      "original_language": "en",
      "original_title": "The Debt Collector",
      "overview": "A classically-trained martial artist goes to work as a debt collector for the mob. The job seems easy enough, until one “client” pulls him into a situation deeper than could ever be expected.",
      "popularity": 26.37,
      "poster_path": "/5XyuUPoIeEf3guWLQW9lATON84v.jpg",
      "release_date": "2018-06-05",
      "title": "The Debt Collector",
      "video": false,
      "vote_average": 5.9,
      "vote_count": 165
    },
    {
      "adult": false,
      "backdrop_path": "/7HOT2ECWeSjZkllpBKa2WfIcwO9.jpg",
      "genre_ids": [18, 10749],
      "id": 419743,
      "original_language": "en",
      "original_title": "Disobedience",
      "overview": "A woman learns about the death of her Orthodox Jewish father, a rabbi. She returns home and has romantic feelings rekindled for her best childhood friend, who is now married to her cousin.",
      "popularity": 25.206,
      "poster_path": "/skPT4ffWhlmmDOMNEdxOiP6Emfz.jpg",
      "release_date": "2018-11-30",
      "title": "Disobedience",
      "video": false,
      "vote_average": 7,
      "vote_count": 734
    },
    {
      "adult": false,
      "backdrop_path": "/ekP6EVxL81lZ4ivcqPsoZ72rY0h.jpg",
      "genre_ids": [28, 18, 36],
      "id": 449924,
      "original_language": "cn",
      "original_title": "葉問4",
      "overview": "Following the death of his wife, Ip Man travels to San Francisco to ease tensions between the local kung fu masters and his star student, Bruce Lee, while searching for a better future for his son.",
      "popularity": 24.646,
      "poster_path": "/b5cz6BoyHrgBnhfDHOW5hXRWbln.jpg",
      "release_date": "2019-12-19",
      "title": "Ip Man 4: The Finale",
      "video": false,
      "vote_average": 7.2,
      "vote_count": 1679
    },
    {
      "adult": false,
      "backdrop_path": "/b8EeJnKkjatM3b0dvWpQOKNf0vN.jpg",
      "genre_ids": [53],
      "id": 602147,
      "original_language": "en",
      "original_title": "Inheritance",
      "overview": "The patriarch of a wealthy and powerful family suddenly passes away, leaving his wife and daughter with a shocking secret inheritance that threatens to unravel and destroy their lives.",
      "popularity": 20.698,
      "poster_path": "/l13mt3oHErSkkqJbN1bjzgtK0Vq.jpg",
      "release_date": "2020-04-30",
      "title": "Inheritance",
      "video": false,
      "vote_average": 6.3,
      "vote_count": 474
    },
    {
      "adult": false,
      "backdrop_path": "/zh1M8fE2vQ0BKxYzIvMYan7ryV.jpg",
      "genre_ids": [878, 18, 53, 27],
      "id": 549294,
      "original_language": "en",
      "original_title": "Synchronic",
      "overview": "Two New Orleans paramedics' lives are ripped apart after encountering a series of horrific deaths linked to a designer drug with bizarre, otherworldly effects.",
      "popularity": 18.736,
      "poster_path": "/wgm4gdJwb7iSYX0uBsRAZmHQmPm.jpg",
      "release_date": "2020-10-23",
      "title": "Synchronic",
      "video": false,
      "vote_average": 6.3,
      "vote_count": 641
    },
    {
      "adult": false,
      "backdrop_path": "/1MXgIE5wLCUynW6PGmM0rLDJAaP.jpg",
      "genre_ids": [18, 28, 36],
      "id": 14756,
      "original_language": "cn",
      "original_title": "葉問",
      "overview": "A semi-biographical account of Yip Man, the first martial arts master to teach the Chinese martial art of Wing Chun. The film focuses on events surrounding Ip that took place in the city of Foshan between the 1930s to 1940s during the Second Sino-Japanese War. Directed by Wilson Yip, the film stars Donnie Yen in the lead role, and features fight choreography by Sammo Hung.",
      "popularity": 17.655,
      "poster_path": "/ggTTUXZg7trvAhsVj3eyd65bAnh.jpg",
      "release_date": "2008-12-12",
      "title": "Ip Man",
      "video": false,
      "vote_average": 7.7,
      "vote_count": 3267
    },
    {
      "adult": false,
      "backdrop_path": "/98sIdYdvnh68Va1JLjcyAuFGZO5.jpg",
      "genre_ids": [18, 80, 53],
      "id": 466081,
      "original_language": "en",
      "original_title": "The Informer",
      "overview": "In New York, former convict Pete Koslow, related to the Polish mafia, must deal with both Klimek the General, his ruthless boss, and the twisted ambitions of two federal agents, as he tries to survive and protect the lives of his loved ones.",
      "popularity": 17.437,
      "poster_path": "/pbGveUC8mk0QRkdXpERPLbMFnrg.jpg",
      "release_date": "2019-08-30",
      "title": "The Informer",
      "video": false,
      "vote_average": 6.5,
      "vote_count": 668
    },
    {
      "adult": false,
      "backdrop_path": "/wONHmd6x0UW6AV1DLzxlNwH9sQn.jpg",
      "genre_ids": [53, 36, 18],
      "id": 393624,
      "original_language": "en",
      "original_title": "Official Secrets",
      "overview": "The true story of British intelligence whistleblower Katharine Gun who—prior to the 2003 Iraq invasion—leaked a top-secret NSA memo exposing a joint US-UK illegal spying operation against members of the UN Security Council. The memo proposed blackmailing member states into voting for war.",
      "popularity": 15.873,
      "poster_path": "/lyCGqSkT3PqLYQXiWs4FCVJBAYW.jpg",
      "release_date": "2019-08-30",
      "title": "Official Secrets",
      "video": false,
      "vote_average": 7.2,
      "vote_count": 776
    },
    {
      "adult": false,
      "backdrop_path": "/2kfkOigqC6B3P7UVB332EC0Eyz3.jpg",
      "genre_ids": [12, 35, 18],
      "id": 371645,
      "original_language": "en",
      "original_title": "Hunt for the Wilderpeople",
      "overview": "Ricky is a defiant young city kid who finds himself on the run with his cantankerous foster uncle in the wild New Zealand bush. A national manhunt ensues, and the two are forced to put aside their differences and work together to survive.",
      "popularity": 15.112,
      "poster_path": "/hkmz9rxgcweizXNElozGeKwmAJE.jpg",
      "release_date": "2016-03-31",
      "title": "Hunt for the Wilderpeople",
      "video": false,
      "vote_average": 7.7,
      "vote_count": 1762
    },
    {
      "adult": false,
      "backdrop_path": "/fSFlM6V8dHTzoCgH1sxxYfRYYUd.jpg",
      "genre_ids": [18, 28, 36, 53],
      "id": 47854,
      "original_language": "cn",
      "original_title": "精武風雲",
      "overview": "The Japanese forces occupy Shanghai and slowly start spreading terror in the city. Chen Zhen, who was presumed dead, returns to fight against the Japanese and put an end to their tyrannical rule.",
      "popularity": 14.728,
      "poster_path": "/qT6KI2jNiskkB4VuNz4uN0ng4Ro.jpg",
      "release_date": "2010-09-01",
      "title": "Legend of the Fist: The Return of Chen Zhen",
      "video": false,
      "vote_average": 6.7,
      "vote_count": 241
    },
    {
      "adult": false,
      "backdrop_path": "/7Nq8eqXjE1mpeRlGev6ArjTFoZA.jpg",
      "genre_ids": [18, 80],
      "id": 314572,
      "original_language": "es",
      "original_title": "El patrón, radiografía de un crimen",
      "overview": "This incredibly disturbing story follows the exploitation of an apprentice butcher, Hermógenes, and his trial after he murders his boss in broad daylight. Hermógenes, a farmhand from northern Argentina, relocates to Buenos Aires in search of a better life for himself and his young wife, but soon finds himself at the mercy of a corrupt boss. The film is based on a thorough investigation of a real event that happened in Buenos Aires 10 years ago. Almost every scene in the film is inspired by real facts or based on well documented daily practices of the “meat business” and its environment. Both a shocking exposé of unscrupulous practices in the meat industry and a heart-wrenching personal story, El Patrón became one of the most successful Argentine films of 2014.",
      "popularity": 14.722,
      "poster_path": "/tqM5b356wYON9VcIKUTOONRUL7P.jpg",
      "release_date": "2014-10-12",
      "title": "The Boss: Anatomy of a Crime",
      "video": false,
      "vote_average": 7.7,
      "vote_count": 83
    },
    {
      "adult": false,
      "backdrop_path": "/zW0hp6O61wzWhf1IES7raTBpSS4.jpg",
      "genre_ids": [18],
      "id": 336011,
      "original_language": "en",
      "original_title": "White Girl",
      "overview": "Summer, New York City. A college girl falls hard for a guy she just met. After a night of partying goes wrong, she goes to wild extremes to get him back.",
      "popularity": 14.559,
      "poster_path": "/zBmIjDObX0qMQbTWn3qBAANopUx.jpg",
      "release_date": "2016-09-02",
      "title": "White Girl",
      "video": false,
      "vote_average": 5.7,
      "vote_count": 416
    },
    {
      "adult": false,
      "backdrop_path": "/9HyNgy6xYikHRP3veDN26AwCLsB.jpg",
      "genre_ids": [28, 53],
      "id": 531503,
      "original_language": "en",
      "original_title": "Point Blank",
      "overview": "A nurse is forced to spring a wounded murder suspect from the hospital when the man’s brother kidnaps his pregnant wife and wants to make a trade.",
      "popularity": 14.414,
      "poster_path": "/weAvkxl0dnPevIKD8fwHjiOi6tc.jpg",
      "release_date": "2019-07-12",
      "title": "Point Blank",
      "video": false,
      "vote_average": 6.1,
      "vote_count": 469
    },
    {
      "adult": false,
      "backdrop_path": "/s75CDPm61dDM7C5STW884J6uFk1.jpg",
      "genre_ids": [18],
      "id": 453755,
      "original_language": "en",
      "original_title": "Arctic",
      "overview": "A man stranded in the Arctic is finally about to receive his long awaited rescue. However, after a tragic accident, his opportunity is lost and he must then decide whether to remain in the relative safety of his camp or embark on a deadly trek through the unknown for potential salvation.",
      "popularity": 13.909,
      "poster_path": "/dxRc0Y4IjSRLC2fYaguXQtJCI4e.jpg",
      "release_date": "2018-11-21",
      "title": "Arctic",
      "video": false,
      "vote_average": 6.5,
      "vote_count": 1029
    }
  ],
  "total_pages": 6,
  "total_results": 107
}
